pypi_pack/__init__.py
pypi_pack/pypi_modu.py
codesignal_onetotwo-0.0.1.dist-info/LICENCE
codesignal_onetotwo-0.0.1.dist-info/METADATA
codesignal_onetotwo-0.0.1.dist-info/WHEEL
codesignal_onetotwo-0.0.1.dist-info/top_level.txt
codesignal_onetotwo-0.0.1.dist-info/RECORD
