Metadata-Version: 2.1
Name: codesignal-onetotwo
Version: 0.0.1
Summary: first_five_codesignal_problems
Home-page: https://github.com/pypa/sampleproject
Author: priyatham
Author-email: priyatham.chanti21@gmail.com
License: UNKNOWN
Platform: UNKNOWN
Classifier: Programming Language :: Python :: 3
Classifier: License :: OSI Approved :: MIT License
Classifier: Operating System :: OS Independent
Requires-Python: >=3.7
